{
  "Name": "All mein Gedanken",
  "Composer": "Anette von Droste-Hülshoff",
  "Source/Collection": "Weihnachtslieder von Komponistinnen, Bd. 3",
  "Publication Year": "",
  "First Performance": "",
  "Duration": "",
  "Availability": "Published",
  "Link to Score": "https://furore-verlag.de/en/produkt/christmas-carols-by-women-composers-cd-music-publications/",
  "links": [
    "https://furore-verlag.de/en/produkt/christmas-carols-by-women-composers-cd-music-publications/",
    "https://furore-verlag.de/en/shop/?filtering=1&filter_product_brand=1240,1132,1024,1180,1036"
  ],
  "Status": "Complete",
  "Notes": "",
  "Genre": "Vocal",
  "SubGenre": "Lieder",
  "Period": "Romantic",
  "Instrumentation": [],
  "Related Works": [],
  "Long Description": "",
  "Short Description": "",
  "tags": [],
  "Catalog Number": "fue 7850",
  "ISMN": "",
  "publisher": "Furore",
  "name of source": "Anette_von_Droste-Hülshoff_All_mein_Gedanken.txt"
}