{
  "Name": "...QUE DES ÂMES",
  "Composer": "Carmen Maria Cârneci",
  "Source/Collection": "",
  "Publication Year": "1990/91",
  "First Performance": "",
  "Duration": "12'",
  "Availability": "Published",
  "Link to Score": "https://furore-verlag.de/wp-content/uploads/2021/01/Gesamtkatalog_vokal_screen.pdf",
  "links": [
    "https://furore-verlag.de/wp-content/uploads/2021/01/Gesamtkatalog_vokal_screen.pdf"
  ],
  "Status": "Complete",
  "Notes": "",
  "Genre": "Vocal",
  "SubGenre": "Ensemble",
  "Period": "Contemporary",
  "Instrumentation": [
    "soprano",
    "soprano",
    "mezzo-soprano",
    "mezzo-soprano",
    "alto",
    "alto"
  ],
  "Related Works": [],
  "Long Description": "",
  "Short Description": "QUARTETTE UND ENSEMBLES A CAPPELLA Quartets and Ensembles unaccompanied",
  "tags": [],
  "Catalog Number": "fue 6170",
  "ISMN": "979-0-50012-617-1",
  "publisher": "Furore",
  "name of source": "Carmen_Maria_Cârneci_QUE_DES_ÂMES.txt"
}