{
  "Name": "Im Wald \"Im Wald, im hellen Sonnenschein\"",
  "Composer": "Fanny Hensel geb. Mendelssohn",
  "Source/Collection": "",
  "Publication Year": "",
  "First Performance": "",
  "Duration": "3'04",
  "Availability": "Published",
  "Link to Score": "https://furore-verlag.de/en/produkt/weltliche-a-cappella-choere-von-1846-vol-1/",
  "links": [
    "https://furore-verlag.de/en/produkt/weltliche-a-cappella-choere-von-1846-vol-1/",
    "https://furore-verlag.de/wp-content/uploads/2021/11/Fanny-Hensel-Katalog-2022-1.pdf",
    "https://furore-verlag.de/wp-content/uploads/2021/01/Gesamtkatalog_vokal_screen.pdf"
  ],
  "Status": "Complete",
  "Notes": "Part of the Deutscher Chorwettbewerb - Auswahlliste",
  "Genre": "Vocal",
  "SubGenre": "Lieder",
  "Period": "Romantic",
  "Instrumentation": [],
  "Related Works": [
    "Lockung \"Hörst du nicht die Bäume rauschen\"",
    "Abendlich \"Abendlich schon rauscht der Wald\""
  ],
  "Long Description": "",
  "Short Description": "A vocal piece by Fanny Hensel geb. Mendelssohn, part of a collection for the Deutscher Chorwettbewerb",
  "tags": [],
  "Catalog Number": "fue 5100",
  "ISMN": "979-0-50012-221-0",
  "publisher": "Furore",
  "name of source": "Fanny_Hensel_geb_Mendelssohn_Heft_1Vol_1.txt"
}