{
  "Name": "Dixit Dominus",
  "Composer": "Maria Rosa Coccia",
  "Source/Collection": "",
  "Publication Year": "",
  "First Performance": "",
  "Duration": "",
  "Availability": "Published",
  "Link to Score": "https://furore-verlag.de/en/product-category/music-publications/?filtering=1&filter_product_brand=1180%2C1396%2C1044%2C1268%2C836%2C7208%2C7256&product_orderby=price",
  "links": [
    "https://furore-verlag.de/en/product-category/music-publications/?filtering=1&filter_product_brand=1180%2C1396%2C1044%2C1268%2C836%2C7208%2C7256&product_orderby=price",
    "https://furore-verlag.de/en/produkt-schlagwort/classical-music/?add-to-cart=557",
    "https://furore-verlag.de/en/produkt-schlagwort/18th-century/?filtering=1&filter_product_brand=1028,1088,1284,784,744,796,716,1324,760,1048,1144,836"
  ],
  "Status": "Complete",
  "Notes": "",
  "Genre": "Choral",
  "SubGenre": "Motet",
  "Period": "Baroque",
  "Instrumentation": [],
  "Related Works": [],
  "Long Description": "",
  "Short Description": "",
  "tags": [],
  "Catalog Number": "fue 5620, S. 20",
  "ISMN": "",
  "publisher": "Furore",
  "name of source": "Maria_Rosa_Coccia_Dixit_Dominus.txt",
  "composer_id": 1699
}